docker_monitor/__init__.py
docker_monitor/main.py
docker_monitor/assets/docker-monitor-manager-128x128.png
docker_monitor/assets/docker-monitor-manager-16x16.png
docker_monitor/assets/docker-monitor-manager-256x256.png
docker_monitor/assets/docker-monitor-manager-32x32.png
docker_monitor/assets/docker-monitor-manager-48x48.png
docker_monitor/assets/docker-monitor-manager-512x512.png
docker_monitor/assets/docker-monitor-manager-64x64.png
docker_monitor/assets/docker-monitor-manager.svg
docker_monitor/assets/icon.png
docker_monitor/cli/__init__.py
docker_monitor/cli/config.py
docker_monitor/cli/doctor.py
docker_monitor/cli/help.py
docker_monitor/cli/setup.py
docker_monitor/cli/test.py
docker_monitor/cli/uninstall.py
docker_monitor/cli/update.py
docker_monitor/gui/__init__.py
docker_monitor/gui/docker_monitor_app.py
docker_monitor/gui/managers/__init__.py
docker_monitor/gui/managers/container_manager.py
docker_monitor/gui/managers/image_manager.py
docker_monitor/gui/managers/info_display_manager.py
docker_monitor/gui/managers/network_manager.py
docker_monitor/gui/managers/prune_manager.py
docker_monitor/gui/managers/system_manager.py
docker_monitor/gui/managers/volume_manager.py
docker_monitor/gui/widgets/__init__.py
docker_monitor/gui/widgets/copy_tooltip.py
docker_monitor/gui/widgets/docker_terminal.py
docker_monitor/gui/widgets/ui_components.py
docker_monitor/utils/__init__.py
docker_monitor/utils/buffer_handler.py
docker_monitor/utils/docker_utils.py
docker_monitor_manager-1.0.9.dist-info/licenses/LICENSE
setup_tools/README.md
setup_tools/__init__.py
setup_tools/create_icons.sh
setup_tools/docker-monitor-manager.desktop
setup_tools/post_install.py
setup_tools/uninstall.py
setup_tools/icons/.gitkeep
setup_tools/icons/README.md
setup_tools/icons/docker-monitor-manager-128x128.png
setup_tools/icons/docker-monitor-manager-16x16.png
setup_tools/icons/docker-monitor-manager-256x256.png
setup_tools/icons/docker-monitor-manager-32x32.png
setup_tools/icons/docker-monitor-manager-48x48.png
docker_monitor_manager-1.0.9.dist-info/METADATA
docker_monitor_manager-1.0.9.dist-info/WHEEL
docker_monitor_manager-1.0.9.dist-info/entry_points.txt
docker_monitor_manager-1.0.9.dist-info/top_level.txt
docker_monitor_manager-1.0.9.dist-info/RECORD
