Metadata-Version: 2.4
Name: docker-monitor-manager
Version: 1.0.9
Summary: A powerful desktop tool for monitoring and managing Docker containers
Home-page: https://github.com/amir-khoshdel-louyeh/docker-monitor-manager
Author: Amir Khoshdel Louyeh
Author-email: Amir Khoshdel Louyeh <amirkhoshdellouyeh@gmail.com>
License: MIT
Project-URL: Homepage, https://github.com/amir-khoshdel-louyeh/docker-monitor-manager
Project-URL: Repository, https://github.com/amir-khoshdel-louyeh/docker-monitor-manager
Project-URL: Issues, https://github.com/amir-khoshdel-louyeh/docker-monitor-manager/issues
Keywords: docker,monitoring,containers,gui,desktop,management
Classifier: Development Status :: 5 - Production/Stable
Classifier: Intended Audience :: Developers
Classifier: Intended Audience :: System Administrators
Classifier: Topic :: System :: Systems Administration
Classifier: License :: OSI Approved :: MIT License
Classifier: Programming Language :: Python :: 3
Classifier: Programming Language :: Python :: 3.8
Classifier: Programming Language :: Python :: 3.9
Classifier: Programming Language :: Python :: 3.10
Classifier: Programming Language :: Python :: 3.11
Classifier: Programming Language :: Python :: 3.12
Classifier: Operating System :: OS Independent
Classifier: Topic :: System :: Monitoring
Requires-Python: >=3.8
License-File: LICENSE
Requires-Dist: docker>=6.0.0
Requires-Dist: Pillow>=9.0.0
Dynamic: author
Dynamic: home-page
Dynamic: license-file
Dynamic: requires-python
